LICENSE
README.md
setup.py
cushy_socket/__init__.py
cushy_socket/tcp.py
cushy_socket.egg-info/PKG-INFO
cushy_socket.egg-info/SOURCES.txt
cushy_socket.egg-info/dependency_links.txt
cushy_socket.egg-info/top_level.txt
tests/test_cstcp_client.py
tests/test_cstcp_server.py