Metadata-Version: 2.1
Name: cushy-socket
Version: 1.2.2
Summary: A lightweight socket library
Home-page: https://github.com/Undertone0809/cushy-socket
Author: Zeeland
Author-email: zeeland@foxmail.com
License: Apache 2.0
Keywords: socket,tcp,udp,cushy-socket
Classifier: Development Status :: 3 - Alpha
Classifier: Intended Audience :: Developers
Classifier: Programming Language :: Python :: 3
Classifier: Programming Language :: Python :: 3.7
Classifier: Programming Language :: Python :: 3.8
Classifier: Programming Language :: Python :: 3.9
Classifier: Programming Language :: Python :: 3.10
Classifier: Programming Language :: Python :: 3 :: Only
Classifier: License :: OSI Approved :: MIT License
Classifier: Operating System :: OS Independent
License-File: LICENSE
